build/lib/build/lib/parflow/__init__.py
build/lib/build/lib/parflow/cli/__init__.py
build/lib/build/lib/parflow/cli/compare_pdi_pfb.py
build/lib/build/lib/parflow/cli/pfdist_sort.py
build/lib/build/lib/parflow/cli/tcl2py.py
build/lib/build/lib/parflow/tools/__init__.py
build/lib/build/lib/parflow/tools/builders.py
build/lib/build/lib/parflow/tools/compare.py
build/lib/build/lib/parflow/tools/core.py
build/lib/build/lib/parflow/tools/export.py
build/lib/build/lib/parflow/tools/fs.py
build/lib/build/lib/parflow/tools/helper.py
build/lib/build/lib/parflow/tools/hydrology.py
build/lib/build/lib/parflow/tools/io.py
build/lib/build/lib/parflow/tools/pf_backend.py
build/lib/build/lib/parflow/tools/settings.py
build/lib/build/lib/parflow/tools/terminal.py
build/lib/build/lib/parflow/tools/top.py
build/lib/build/lib/parflow/tools/util.py
build/lib/build/lib/parflow/tools/database/__init__.py
build/lib/build/lib/parflow/tools/database/core.py
build/lib/build/lib/parflow/tools/database/domains.py
build/lib/build/lib/parflow/tools/database/generated.py
build/lib/build/lib/parflow/tools/database/handlers.py
build/lib/build/lib/parflow/tools/ref/reservoir_keys.yaml
build/lib/build/lib/parflow/tools/ref/subsurface_conus_1.txt
build/lib/build/lib/parflow/tools/ref/subsurface_freeze_cherry.txt
build/lib/build/lib/parflow/tools/ref/subsurface_washita.txt
build/lib/build/lib/parflow/tools/ref/table_keys.yaml
build/lib/build/lib/parflow/tools/ref/vegp_header.txt
build/lib/build/lib/parflow/tools/ref/vegp_igbp.txt
build/lib/build/lib/parflow/tools/ref/vegp_keys.yaml
build/lib/build/lib/parflow/tools/tests/__init__.py
build/lib/build/lib/parflow/tools/tests/pfb_summary.py
build/lib/build/lib/parflow/tools/tests/test_pf_xarray.py
build/lib/build/lib/parflow/tools/tests/data/__init__.py
build/lib/parflow/__init__.py
build/lib/parflow/cli/__init__.py
build/lib/parflow/cli/compare_pdi_pfb.py
build/lib/parflow/cli/pfdist_sort.py
build/lib/parflow/cli/tcl2py.py
pftools-1.3.14.dist-info/METADATA
pftools-1.3.14.dist-info/WHEEL
pftools-1.3.14.dist-info/entry_points.txt
pftools-1.3.14.dist-info/top_level.txt
pftools-1.3.14.dist-info/RECORD
