Metadata-Version: 2.4
Name: pftools
Version: 1.3.14
Summary: A Python package creating an interface with the ParFlow hydrologic model.
Author-email: HydroFrame <parflow@parflow.org>
Maintainer-email: HydroFrame <parflow@parflow.org>
License: BSD
Project-URL: Homepage, https://github.com/parflow/parflow/tree/master/pftools/python
Project-URL: Repository, https://github.com/parflow/parflow
Project-URL: Documentation, https://parflow.readthedocs.io/en/latest/
Keywords: ParFlow,groundwater model,surface water model
Classifier: Programming Language :: Python :: 3
Classifier: License :: OSI Approved :: BSD License
Requires-Python: >=3.7
Requires-Dist: pyyaml==6.0.1
Requires-Dist: xarray
Requires-Dist: pandas
Requires-Dist: numba
Requires-Dist: numpy
Requires-Dist: dask
Provides-Extra: all
Requires-Dist: imageio>=2.9.0; extra == "all"
Requires-Dist: h5py; extra == "all"
Requires-Dist: twine; extra == "all"
Requires-Dist: black; extra == "all"
Provides-Extra: pfsol
Requires-Dist: imageio>=2.9.0; extra == "pfsol"
Provides-Extra: pdi
Requires-Dist: h5py; extra == "pdi"
Provides-Extra: dev
Requires-Dist: twine; extra == "dev"
Requires-Dist: black; extra == "dev"
